{"name":"build-javascript","namedChunkGroups":{"polyfill":{"name":"polyfill","assets":[{"name":"webpack-runtime-339067f3c16b347b6380.js","size":4976},{"name":"polyfill-7028182706005ccb8e3f.js","size":85868}],"filteredAssets":0,"assetsSize":90844,"filteredAuxiliaryAssets":2,"auxiliaryAssetsSize":228042},"app":{"name":"app","assets":[{"name":"webpack-runtime-339067f3c16b347b6380.js","size":4976},{"name":"framework-0658a0f43daf44de8ecb.js","size":130509},{"name":"app-5d78b624ea2f38f84782.js","size":133477}],"filteredAssets":0,"assetsSize":268962,"filteredAuxiliaryAssets":3,"auxiliaryAssetsSize":949912},"component---src-pages-index-jsx":{"name":"component---src-pages-index-jsx","assets":[{"name":"framework-0658a0f43daf44de8ecb.js","size":130509},{"name":"styles.ac85e0a7802476e830e3.css","size":192137},{"name":"component---src-pages-index-jsx-85a549673761c6aea8e9.js","size":68654}],"filteredAssets":0,"assetsSize":391300,"filteredAuxiliaryAssets":3,"auxiliaryAssetsSize":739743}},"assetsByChunkName":{"polyfill":["webpack-runtime-339067f3c16b347b6380.js","polyfill-7028182706005ccb8e3f.js"],"app":["webpack-runtime-339067f3c16b347b6380.js","framework-0658a0f43daf44de8ecb.js","app-5d78b624ea2f38f84782.js"],"component---src-pages-index-jsx":["framework-0658a0f43daf44de8ecb.js","styles.ac85e0a7802476e830e3.css","component---src-pages-index-jsx-85a549673761c6aea8e9.js"]},"childAssetsByChunkName":{}}