{
  "Professional": [
    {
      "title": "EventManager Microservice",
      "desc": "Receives and processes loan events from client-side software for various new web-based data analysis displays. I developed both the data model and all of the API code.",
      "links": [
        {
          "type": "live",
          "url": "https://dev-ui.ltk.ai/"
        },
        {
          "title": "Lender Toolkit",
          "type": "company",
          "url": "https://www.lendertoolkit.com/"
        }
      ],
      "lang": "Backend",
      "tags": [
        "Node.js",
        "DynamoDB",
        "Docker",
        "Terraform"
      ]
    },
    {
      "title": "Rx Card Microservice",
      "desc": "Generates pharmacy cards for new customers. I did the backend development and solved key problems including PDF generation and linking the card info to the company's internal customer-interaction API (which I also developed).",
      "links": [
        {
          "type": "live",
          "url": "https://policyscout.com/rx/download"
        },
        {
          "title": "PolicyScout",
          "type": "company",
          "url": "https://policyscout.com"
        }
      ],
      "lang": "Backend",
      "tags": [
        "Node.js",
        "Serverless Framework",
        "AWS Lambda",
        "DynamoDB"
      ]
    },
    {
      "title": "YardSearch",
      "desc": "Offers junkyard data aggregation and vehicle searching. I developed both a front-end and a back-end for the client.",
      "links": [
        {
          "type": "live",
          "url": "https://yardsearch.tk/"
        },
        {
          "title": "Ensign Technical Solutions",
          "type": "company",
          "url": ""
        }
      ],
      "lang": "Full-Stack",
      "tags": [
        "Vue.js",
        "Bootstrap",
        "Node.js",
        "Koa",
        "MongoDB",
        "Web Scraping"
      ]
    }
  ],
  "Personal": [
    {
      "title": "Modern ePortfolio",
      "desc": "The site you're currently browsing.",
      "links": [
        {
          "type": "live",
          "url": "http://www.zachc.cf/"
        },
        {
          "title": "GitHub",
          "type": "source",
          "url": "https://github.com/caldwellz/caldwellz.github.io"
        }
      ],
      "lang": "Front-End",
      "tags": [
        "React",
        "Gatsby",
        "Bootstrap",
        "GitHub Pages"
      ]
    },
    {
      "title": "Classic ePortfolio",
      "desc": "The previous, legacy version of this site.",
      "links": [
        {
          "type": "live",
          "url": "http://www.zachc.cf/classic/"
        },
        {
          "title": "GitHub",
          "type": "source",
          "url": "https://github.com/caldwellz/caldwellz.github.io/tree/master/classic"
        }
      ],
      "lang": "Front-End",
      "tags": [
        "Pure HTML/CSS/JS",
        "jQuery",
        "GitHub Pages"
      ]
    },
    {
      "title": "CarTracker",
      "desc": "Tracks changes (particularly price drops) to local classified listings for certain types of automobiles. The backend data API is now working for the types of data analysis I wanted to do; a frontend is in progress.",
      "links": [
        {
          "type": "live",
          "url": "https://app-demo.tk/api/cartracker/stats/all"
        },
        {
          "title": "GitHub",
          "type": "source",
          "url": "https://github.com/caldwellz/CarTracker"
        }
      ],
      "lang": "Full-Stack",
      "tags": [
        "Node.js",
        "Express",
        "React",
        "Vite",
        "Web Scraping"
      ]
    },
    {
      "title": "Xelandria",
      "desc": "2D browser-based game engine experiment.",
      "links": [
        {
          "type": "live",
          "url": "http://www.zachc.cf/classic/webprojects/xelandria/"
        },
        {
          "title": "GitHub",
          "type": "source",
          "url": "https://github.com/caldwellz/xelandria"
        }
      ],
      "lang": "Front-End",
      "tags": [
        "PixiJS",
        "WebGL"
      ]
    },
    {
      "title": "Project Zorg",
      "desc": "Hybrid text-based adventure game experiment.",
      "links": [
        {
          "type": "live",
          "url": "http://www.zachc.cf/classic/webprojects/project-zorg/"
        },
        {
          "title": "GitHub",
          "type": "source",
          "url": "https://github.com/caldwellz/project-zorg"
        }
      ],
      "lang": "Front-End",
      "tags": [
        "AJAX",
        "LocalStorage",
        "Unicode"
      ]
    },
    {
      "title": "YAMS Emulator",
      "desc": "Emulator for an in-development m68k-based retrocomputer.",
      "links": [
        {
          "title": "GitHub",
          "type": "source",
          "url": "https://github.com/caldwellz/yams-emulator"
        }
      ],
      "lang": "C / C++",
      "tags": [
        "SDL",
        "Meson",
        "Doxygen"
      ]
    },
    {
      "title": "Xeno",
      "desc": "Xbox/NXDK game engine experiment.",
      "links": [
        {
          "title": "GitHub",
          "type": "source",
          "url": "https://github.com/caldwellz/xeno"
        }
      ],
      "lang": "C / C++",
      "tags": [
        "SDL"
      ]
    },
    {
      "title": "Jammy Dodge Rover",
      "desc": "Raspberry Pi-based Bluetooth RC platform.",
      "links": [
        {
          "title": "Zip File",
          "type": "source",
          "url": "http://www.zachc.cf/classic/eportfolio/electronics/RoverScripts.zip"
        }
      ],
      "lang": "Python",
      "tags": [
        "PyBluez"
      ]
    }
  ],
  "Academic": [
    {
      "title": "The Mountain Spoke",
      "desc": "Term project for CIT 230 (Front-End Web Development I).",
      "links": [
        {
          "type": "live",
          "url": "http://www.zachc.cf/classic/eportfolio/cit230/assignments/term-project/"
        },
        {
          "title": "GitHub",
          "type": "source",
          "url": "https://github.com/caldwellz/caldwellz.github.io/tree/master/classic/eportfolio/cit230/assignments/term-project"
        }
      ],
      "lang": "Front-End",
      "tags": [
        "Google Maps",
        "jQuery"
      ]
    },
    {
      "title": "Tri-City Paper Pilots",
      "desc": "Midterm project for CIT 230 (Front-End Web Development I).",
      "links": [
        {
          "type": "live",
          "url": "http://www.zachc.cf/classic/eportfolio/cit230/assignments/weathersite/"
        },
        {
          "title": "GitHub",
          "type": "source",
          "url": "https://github.com/caldwellz/caldwellz.github.io/tree/master/classic/eportfolio/cit230/assignments/weathersite"
        }
      ],
      "lang": "Front-End",
      "tags": []
    },
    {
      "title": "WDD 330 (Web Dev) Portfolio",
      "desc": "Course portfolio for WDD 330 (Front-End Web Development II).",
      "links": [
        {
          "type": "live",
          "url": "http://www.zachc.cf/classic/eportfolio/wdd330/"
        },
        {
          "title": "GitHub",
          "type": "source",
          "url": "https://github.com/caldwellz/caldwellz.github.io/tree/master/classic/eportfolio/wdd330"
        }
      ],
      "lang": "Front-End",
      "tags": [
        "AJAX",
        "LocalStorage"
      ]
    },
    {
      "title": "CS 124 (C++) Assignments",
      "desc": "Function-oriented programming assignments completed at BYU-Idaho.",
      "links": [
        {
          "title": "GitHub",
          "type": "source",
          "url": "https://github.com/caldwellz/college-software-development/tree/main/C%2B%2B%20-%20CS%20124%20(Intro%20to%20Software%20Development)"
        }
      ],
      "lang": "C++",
      "tags": []
    },
    {
      "title": "CS 165 (C++) Assignments",
      "desc": "Object-oriented programming assignments completed at BYU-Idaho.",
      "links": [
        {
          "title": "GitHub",
          "type": "source",
          "url": "https://github.com/caldwellz/college-software-development/tree/main/C%2B%2B%20-%20CS%20165%20(Object-Oriented%20Programming)"
        }
      ],
      "lang": "C++",
      "tags": []
    },
    {
      "title": "CS 235 (C++) Assignments",
      "desc": "Data structure & algorithm programming assignments completed at BYU-Idaho.",
      "links": [
        {
          "title": "GitHub",
          "type": "source",
          "url": "https://github.com/caldwellz/college-software-development/tree/main/C%2B%2B%20-%20CS%20235%20(Data%20Structures)"
        }
      ],
      "lang": "C++",
      "tags": []
    },
    {
      "title": "CIT 260 (Java) Assignments",
      "desc": "Object-oriented programming assignments completed at BYU-Idaho.",
      "links": [
        {
          "title": "GitHub",
          "type": "source",
          "url": "https://github.com/caldwellz/college-software-development/tree/main/Java%20-%20CIT%20260%20(Object-Oriented%20Programming)"
        }
      ],
      "lang": "Java",
      "tags": []
    },
    {
      "title": "PL/SQL Assignments",
      "desc": "Database Development assignments completed during two sequential courses at BYU-Idaho.",
      "links": [
        {
          "title": "GitHub",
          "type": "source",
          "url": "https://github.com/caldwellz/byui-database-development"
        }
      ],
      "lang": "PL/SQL",
      "tags": [
        "Oracle Database"
      ]
    },
    {
      "title": "CS 112 (Python) Assignments",
      "desc": "Introductory programming assignments completed at LDS Business College.",
      "links": [
        {
          "title": "GitHub",
          "type": "source",
          "url": "https://github.com/caldwellz/college-software-development/tree/main/Python%20-%20CS%20112%20(Programming%20Fundamentals)"
        }
      ],
      "lang": "Python",
      "tags": []
    }
  ]
}